krust/__init__.py
krust/pather.py
krust/zip_utils.py
krust/file_utils/__init__.py
krust/file_utils/file_op.py
krust/file_utils/file_stat.py
krust/file_utils/fsmod.py
krust/file_utils/list_file.py
krust/file_utils/ls.py
krust/file_utils/manager.py
krust/file_utils/path.py
krust/file_utils/local_fsmod/__init__.py
krust/file_utils/local_fsmod/copy_file.py
krust/file_utils/local_fsmod/list_file.py
krust/file_utils/local_fsmod/local_fsmod.py
krust/file_utils/local_fsmod/mkdir.py
krust/file_utils/local_fsmod/rm.py
krust/file_utils/local_fsmod/utils.py
krust-0.0.10.dist-info/DESCRIPTION.rst
krust-0.0.10.dist-info/METADATA
krust-0.0.10.dist-info/RECORD
krust-0.0.10.dist-info/WHEEL
krust-0.0.10.dist-info/metadata.json
krust-0.0.10.dist-info/top_level.txt
tests/__init__.py
tests/test_pather.py
