Metadata-Version: 2.0
Name: krust
Version: 0.0.10
Summary: Shell utils
Home-page: https://github.com/claydodo/krust
Author: claydodo and his little friends (xiao huo ban)
Author-email: claydodo@foxmail.com
License: UNKNOWN
Platform: UNKNOWN
Classifier: Programming Language :: Python :: 2.7 
Classifier: Programming Language :: Python :: 3 
Classifier: Operating System :: OS Independent
Requires-Dist: krux (>=0.0.10)
